AUTHORS.rst
LICENSE
MANIFEST.in
README.rst
setup.py
django_vest/__init__.py
django_vest/context_processors.py
django_vest/decorators.py
django_vest/fields.py
django_vest/templates_loaders.py
django_vest/test.py
django_vest/utils.py
django_vest.egg-info/PKG-INFO
django_vest.egg-info/SOURCES.txt
django_vest.egg-info/dependency_links.txt
django_vest.egg-info/not-zip-safe
django_vest.egg-info/requires.txt
django_vest.egg-info/top_level.txt
django_vest/config/__init__.py
django_vest/config/backends.py
django_vest/config/config.py
django_vest/templatetags/__init__.py
django_vest/templatetags/vest_tags.py