Metadata-Version: 1.1
Name: django-vest
Version: 0.1.6
Summary: Extension for default template system for making inheritance more flexible. Adding some kind of themes.
Home-page: https://github.com/zerc/django-vest
Author: Vladimir Savin
Author-email: zero13cool@yandex.ru
License: MIT
Keywords: django-vest
Platform: UNKNOWN
Classifier: Development Status :: 2 - Pre-Alpha
Classifier: Intended Audience :: Developers
Classifier: License :: OSI Approved :: MIT License
Classifier: Natural Language :: English
Classifier: Programming Language :: Python :: 2
Classifier: Programming Language :: Python :: 2.7
Classifier: Programming Language :: Python :: 3
Classifier: Programming Language :: Python :: 3.3
Classifier: Programming Language :: Python :: 3.4
